{
    "pilotos": [
        {
            "id": 1,
            "nome": "Pierre Gasly",
            "equipe": "Alpine",
            "nacionalidade": "assets/images/franca.jpg",
            "numero": 10,
            "idade": 30,
            "titulos": 0,
            "vitorias": 0,
            "descricao": "Piloto experiente da Alpine, consistente no meio de pelotão.",
            "imagem": "assets/images/gasly.jpg"
        },
        {
            "id": 2,
            "nome": "Franco Colapinto",
            "equipe": "Alpine",
            "nacionalidade": "assets/images/argentina.jpg",
            "numero": 43,
            "idade": 23,
            "titulos": 0,
            "vitorias": 0,
            "descricao": "Jovem piloto argentino na Alpine.",
            "imagem": "assets/images/franco.jpg"
        },
        {
            "id": 3,
            "nome": "Fernando Alonso",
            "equipe": "Aston Martin",
            "nacionalidade": "assets/images/espanha.jpg",
            "numero": 14,
            "idade": 44,
            "titulos": 2,
            "vitorias": 32,
            "descricao": "Veterano e bicampeão mundial na Aston Martin.",
            "imagem": "assets/images/alonso.png"
        },
        {
            "id": 4,
            "nome": "Lance Stroll",
            "equipe": "Aston Martin",
            "nacionalidade": "assets/images/canada.jpg",
            "numero": 18,
            "idade": 27,
            "titulos": 0,
            "vitorias": 0,
            "descricao": "Piloto canadense ao lado de Alonso.",
            "imagem": "assets/images/stroll.jpg"
        },
        {
            "id": 5,
            "nome": "Nico Hülkenberg",
            "equipe": "Audi",
            "nacionalidade": "assets/images/alemanha.jpg",
            "numero": 27,
            "idade": 38,
            "titulos": 0,
            "vitorias": 0,
            "descricao": "Piloto alemão experiente liderando o projeto Audi.",
            "imagem": "assets/images/hulkenberg.jpg"
        },
        {
            "id": 6,
            "nome": "Gabriel Bortoleto",
            "equipe": "Audi",
            "nacionalidade": "assets/images/brasil.jpg",
            "numero": 5,
            "idade": 21,
            "titulos": 0,
            "vitorias": 0,
            "descricao": "Promessa brasileira estreando na Fórmula 1.",
            "imagem": "assets/images/bortoleto.jpg"
        },
        
        {
            "id": 7,
            "nome": "Sergio Pérez",
            "equipe": "Cadillac",
            "nacionalidade": "assets/images/mexico.jpg",
            "numero": 11,
            "idade": 36,
            "titulos": 0,
            "vitorias": 6,
            "descricao": "Piloto mexicano experiente e vencedor de GPs.",
            "imagem": "assets/images/perez.jpg"
        },
        {
            "id": 8,
            "nome": "Valtteri Bottas",
            "equipe": "Cadillac",
            "nacionalidade": "assets/images/finlandia.jpg",
            "numero": 77,
            "idade": 36,
            "titulos": 0,
            "vitorias": 10,
            "descricao": "Piloto finlandês com vasta experiência na F1.",
            "imagem": "assets/images/bottas.jpg"
        },
        
        {
            "id": 9,
            "nome": "Charles Leclerc",
            "equipe": "Ferrari",
            "nacionalidade": "assets/images/monaco.jpg",
            "numero": 16,
            "idade": 28,
            "titulos": 0,
            "vitorias": 8,
            "descricao": "Principal nome da Ferrari.",
            "imagem": "assets/images/leclerc.jpg"
        },
        {
            "id": 10,
            "nome": "Lewis Hamilton",
            "equipe": "Ferrari",
            "nacionalidade": "assets/images/reino-unido.jpg",
            "numero": 41,
            "idade": 39,
            "titulos": 7,
            "vitorias": 103,
            "descricao": "Sete vezes campeão mundial.",
            "imagem": "assets/images/hamilton.jpg"
        },
        {
            "id": 11,
            "nome": "Oliver Bearman",
            "equipe": "Haas",
            "nacionalidade": "assets/images/reino-unido.jpg",
            "numero": 87,
            "idade": 20,
            "titulos": 0,
            "vitorias": 0,
            "descricao": "Jovem britânico, talento em ascensão na Haas.",
            "imagem": "assets/images/ollie.jpg"
        },
        {
            "id": 12,
            "nome": "Esteban Ocon",
            "equipe": "Haas",
            "nacionalidade": "assets/images/franca.jpg",
            "numero": 31,
            "idade": 28,
            "titulos": 0,
            "vitorias": 1,
            "descricao": "Experiente piloto francês na Haas.",
            "imagem": "assets/images/ocon.jpg"
        },
        {
            "id": 13,
            "nome": "Lando Norris",
            "equipe": "McLaren",
            "nacionalidade": "assets/images/reino-unido.jpg",
            "numero": 1,
            "idade": 26,
            "titulos": 1,
            "vitorias": 11,
            "descricao": "Piloto britânico rápido e consistente pela McLaren.",
            "imagem": "assets/images/norris.jpg"
        },
        {
            "id": 14,
            "nome": "Oscar Piastri",
            "equipe": "McLaren",
            "nacionalidade": "assets/images/australia.jpg",
            "numero": 81,
            "idade": 24,
            "titulos": 0,
            "vitorias": 6,
            "descricao": "Jovem australiano com grande futuro.",
            "imagem": "assets/images/piastri.jpg"
        },
        {
            "id": 15,
            "nome": "George Russell",
            "equipe": "Mercedes",
            "nacionalidade": "assets/images/reino-unido.jpg",
            "numero": 63,
            "idade": 28,
            "titulos": 0,
            "vitorias": 5,
            "descricao": "Uma das peças centrais da Mercedes.",
            "imagem": "assets/images/russell.jpg"
        },
        {
            "id": 16,
            "nome": "Andrea Kimi Antonelli",
            "equipe": "Mercedes",
            "nacionalidade": "assets/images/italia.jpg",
            "numero": 12,
            "idade": 19,
            "titulos": 0,
            "vitorias": 0,
            "descricao": "Jovem talento italiano fazendo sua estreia.",
            "imagem": "assets/images/antonelli.jpg"
        },
        {
            "id": 17,
            "nome": "Liam Lawson",
            "equipe": "Racing Bulls",
            "nacionalidade": "assets/images/novazelandia.jpg",
            "numero": 30,
            "idade": 23,
            "titulos": 0,
            "vitorias": 0,
            "descricao": "Novo companheiro de Verstappen na Red Bull.",
            "imagem": "assets/images/lawson.jpg"
        },
        {
            "id": 18,
            "nome": "Arvid Lindblad",
            "equipe": "Racing Bulls",
            "nacionalidade": "assets/images/reino-unido.jpg",
            "numero": 41,
            "idade": 18,
            "titulos": 0,
            "vitorias": 0,
            "descricao": "Piloto britânico talentoso na Racing Bulls.",
            "imagem": "assets/images/Lindblad.jpg"
        },
        {
            "id": 19,
            "nome": "Max Verstappen",
            "equipe": "Red Bull",
            "nacionalidade": "assets/images/paises_baixos.jpg",
            "numero": 3,
            "idade": 28,
            "titulos": 4,
            "vitorias": 63,
            "descricao": "Campeão mundial e estrela da Red Bull Racing.",
            "imagem": "assets/images/verstappen.jpg"
        },
        {
            "id": 20,
            "nome": "Isack Hadjar",
            "equipe": "Red Bull",
            "nacionalidade": "assets/images/franca.jpg",
            "numero": 6,
            "idade": 20,
            "titulos": 0,
            "vitorias": 0,
            "descricao": "Piloto francês talentoso na Racing Bulls.",
            "imagem": "assets/images/hadjar.jpg"
        },
        {
            "id": 21,
            "nome": "Alexander Albon",
            "equipe": "Williams",
            "nacionalidade": "assets/images/tailandia.jpg",
            "numero": 23,
            "idade": 28,
            "titulos": 0,
            "vitorias": 0,
            "descricao": "Experiente piloto da Williams.",
            "imagem": "assets/images/albon.jpg"
        },
        {
            "id": 22,
            "nome": "Carlos Sainz",
            "equipe": "Williams",
            "nacionalidade": "assets/images/espanha.jpg",
            "numero": 55,
            "idade": 30,
            "titulos": 0,
            "vitorias": 2,
            "descricao": "Piloto espanhol com experiência na F1.",
            "imagem": "assets/images/sainz.jpg"
        }
    ]
}